catopuma/__init__.py
catopuma/__version__.py
catopuma/feeder.py
catopuma/losses.py
catopuma/metrics.py
catopuma/preprocessing.py
catopuma/uploader.py
catopuma-1.0.0.dev0.dist-info/METADATA
catopuma-1.0.0.dev0.dist-info/WHEEL
catopuma-1.0.0.dev0.dist-info/top_level.txt
catopuma-1.0.0.dev0.dist-info/RECORD
