Metadata-Version: 2.1
Name: catopuma
Version: 1.0.0.dev0
Summary: Custom Advanced Tensorflow Objects to Preprocess, Upload, Model and Augment
Home-page: https://github.com/RiccardoBiondi/Catopuma
Download-URL: https://github.com/RiccardoBiondi/Catopuma
Author: Riccardo Biondi
Author-email: riccardo.biondi7@unibo.it
License: MIT
Keywords: artificial-intelligence deep-learning oop tensorflow keras
Platform: any
Classifier: Programming Language :: Python :: 3
Classifier: Operating System :: OS Independent
Requires-Python: >=3.5
Requires-Dist: numpy
Requires-Dist: keras
Requires-Dist: tensorflow
Requires-Dist: SimpleITK
Requires-Dist: pytest
Requires-Dist: hypothesis
